cli/__init__.py
cli/cli.py
mlvpn-0.2.dist-info/METADATA
mlvpn-0.2.dist-info/WHEEL
mlvpn-0.2.dist-info/entry_points.txt
mlvpn-0.2.dist-info/top_level.txt
mlvpn-0.2.dist-info/RECORD
